.gitignore
.gitmodules
CHANGELOG.rst
COPYING
Makefile
README.rst
setup.py
tox.ini
wendelin.py
3rdparty/ccan
3rdparty/ccan/.gitignore
3rdparty/ccan/.travis.yml
3rdparty/ccan/Makefile
3rdparty/ccan/Makefile-ccan
3rdparty/ccan/Makefile-web
3rdparty/ccan/PATCHES
3rdparty/ccan/README
3rdparty/ccan/ccan/.gitignore
3rdparty/ccan/ccan/a_star/LICENSE
3rdparty/ccan/ccan/a_star/_info
3rdparty/ccan/ccan/a_star/a_star.c
3rdparty/ccan/ccan/a_star/a_star.h
3rdparty/ccan/ccan/a_star/test/run.c
3rdparty/ccan/ccan/aga/LICENSE
3rdparty/ccan/ccan/aga/_info
3rdparty/ccan/ccan/aga/aga.c
3rdparty/ccan/ccan/aga/aga.h
3rdparty/ccan/ccan/aga/bfs.c
3rdparty/ccan/ccan/aga/dfs.c
3rdparty/ccan/ccan/aga/dijkstra.c
3rdparty/ccan/ccan/aga/private.h
3rdparty/ccan/ccan/aga/test/api-adjacency.c
3rdparty/ccan/ccan/aga/test/api-bfs.c
3rdparty/ccan/ccan/aga/test/api-concurrent.c
3rdparty/ccan/ccan/aga/test/api-dfs.c
3rdparty/ccan/ccan/aga/test/api-dijkstra.c
3rdparty/ccan/ccan/aga/test/api-lazytrie-words.txt
3rdparty/ccan/ccan/aga/test/api-lazytrie.c
3rdparty/ccan/ccan/aga/test/chain.c
3rdparty/ccan/ccan/aga/test/compile_fail-mismatch1.c
3rdparty/ccan/ccan/aga/test/compile_fail-mismatch2.c
3rdparty/ccan/ccan/aga/test/compile_fail-mismatch3.c
3rdparty/ccan/ccan/aga/test/compile_fail-mismatch4.c
3rdparty/ccan/ccan/aga/test/compile_ok.c
3rdparty/ccan/ccan/aga/test/error-graph.c
3rdparty/ccan/ccan/aga/test/full.c
3rdparty/ccan/ccan/aga/test/grid.c
3rdparty/ccan/ccan/aga/test/parallel.c
3rdparty/ccan/ccan/aga/test/shortcut1.c
3rdparty/ccan/ccan/aga/test/shortcut2.c
3rdparty/ccan/ccan/aga/test/simple-graph.c
3rdparty/ccan/ccan/aga/test/simple-graph.h
3rdparty/ccan/ccan/aga/test/traversal1.c
3rdparty/ccan/ccan/aga/test/trivial.c
3rdparty/ccan/ccan/agar/LICENSE
3rdparty/ccan/ccan/agar/_info
3rdparty/ccan/ccan/agar/agar.c
3rdparty/ccan/ccan/agar/agar.h
3rdparty/ccan/ccan/agar/test/api-adjacency.c
3rdparty/ccan/ccan/agar/test/api-bfs.c
3rdparty/ccan/ccan/agar/test/api-dfs.c
wendelin.core.egg-info/PKG-INFO
wendelin.core.egg-info/SOURCES.txt
wendelin.core.egg-info/dependency_links.txt
wendelin.core.egg-info/entry_points.txt
wendelin.core.egg-info/requires.txt
wendelin.core.egg-info/top_level.txt