Metadata-Version: 1.1
Name: wendelin.core
Version: 0.13
Summary: Out-of-core NumPy arrays
Home-page: https://lab.nexedi.com/nexedi/wendelin.core
Author: Kirill Smelkov
Author-email: kirr@nexedi.com
License: GPLv3+ with wide exception for Open-Source
Keywords: bigdata out-of-core numpy virtual-memory
Platform: UNKNOWN
Classifier: Development Status :: 5 - Production/Stable
Classifier: Intended Audience :: Developers
Classifier: Intended Audience :: Science/Research
Classifier: Operating System :: POSIX :: Linux
Classifier: Programming Language :: Python :: 2
Classifier: Programming Language :: Python :: 2.7
Classifier: Programming Language :: Python :: 3
Classifier: Programming Language :: Python :: 3.6
Classifier: Programming Language :: Python :: 3.7
Classifier: Programming Language :: Python :: Implementation :: CPython
Classifier: Topic :: Software Development :: Libraries :: Python Modules
Classifier: Framework :: ZODB
